stages/__init__.py
stages/compat.py
stages/stages.py
stages/texts.py
stages-1.0.dev0.dist-info/DESCRIPTION.rst
stages-1.0.dev0.dist-info/METADATA
stages-1.0.dev0.dist-info/RECORD
stages-1.0.dev0.dist-info/WHEEL
stages-1.0.dev0.dist-info/metadata.json
stages-1.0.dev0.dist-info/top_level.txt
