Metadata-Version: 2.0
Name: stages
Version: 1.0.dev0
Summary: Simple support for sequential execution of scripts.
Home-page: UNKNOWN
Author: Tobias Pleyer
Author-email: UNKNOWN
License: BSD
Platform: UNKNOWN
Classifier: Development Status :: 4 - Beta
Classifier: Environment :: Console
Classifier: Intended Audience :: Developers
Classifier: License :: OSI Approved :: BSD License
Classifier: Operating System :: OS Independent
Classifier: Programming Language :: Python
Classifier: Programming Language :: Python :: 2
Classifier: Programming Language :: Python :: 3
Classifier: Topic :: Software Development
Requires-Dist: colorama
Requires-Dist: configparser
